ifoam_denver/__init__.py
ifoam_denver-0.1.dist-info/LICENSE.txt
ifoam_denver-0.1.dist-info/METADATA
ifoam_denver-0.1.dist-info/WHEEL
ifoam_denver-0.1.dist-info/RECORD
