Metadata-Version: 2.1
Name: ifoam-denver
Version: 0.1
Summary: OpenFOAM Development Environment
Home-page: https://github.com/iydon/ifoam-denver
License: GPL-3.0-only
Keywords: OpenFOAM,utilities
Author: Iydon Liang
Author-email: liangiydon@gmail.com
Requires-Python: >=3.7,<4.0
Classifier: Environment :: Console
Classifier: License :: OSI Approved :: GNU General Public License v3 (GPLv3)
Classifier: Natural Language :: Chinese (Simplified)
Classifier: Natural Language :: English
Classifier: Operating System :: Microsoft :: Windows
Classifier: Operating System :: POSIX :: Linux
Classifier: Programming Language :: Python :: 3
Classifier: Programming Language :: Python :: 3.7
Classifier: Programming Language :: Python :: 3.8
Classifier: Programming Language :: Python :: 3.9
Classifier: Programming Language :: Python :: 3.10
Classifier: Programming Language :: Python :: 3.11
Classifier: Programming Language :: Python :: 3.10
Classifier: Programming Language :: Python :: 3.7
Classifier: Programming Language :: Python :: 3.8
Classifier: Programming Language :: Python :: 3.9
Classifier: Topic :: Software Development :: User Interfaces
Classifier: Topic :: Utilities
Classifier: Typing :: Typed
Requires-Dist: click (>=8.1.3,<9.0.0)
Requires-Dist: docker (>=6.0.1,<7.0.0)
Requires-Dist: tomli (>=2.0.1,<3.0.0)
Project-URL: Bug Tracker, https://github.com/iydon/ifoam-denver/issues
Project-URL: Repository, https://github.com/iydon/ifoam-denver
